{
    "name": "fastapi container",
    "dockerComposeFile": [
        "../docker-compose.yml"
    ],
    "service": "app",
    "workspaceFolder": "/application",
    "settings": {
        "python.pythonPath": "/root/.cache/pypoetry/virtualenvs/fast-api-practice-hjPiGOLl-py3.11/bin/python"
    },
    "extensions": [
        "eamodio.gitlens",
        "fabiospampinato.vscode-diff",
        "github.vscode-github-actions",
        "GitHub.vscode-pull-request-github",
        "hbenl.vscode-test-explorer",
        "ionutvmi.path-autocomplete",
        "JoeBerria.statusbarerror",
        "mhutchie.git-graph",
        "mosapride.zenkaku",
        "ms-azuretools.vscode-docker",
        "MS-CEINTL.vscode-language-pack-ja",
        "ms-python.python",
        "ms-python.vscode-pylance",
        "ms-vscode-remote.remote-containers",
        "ms-vscode.makefile-tools",
        "ms-vscode.test-adapter-converter",
        "njpwerner.autodocstring",
        "oderwat.indent-rainbow",
        "PKief.material-icon-theme",
        "sohamkamani.code-eol",
        "streetsidesoftware.code-spell-checker",
        "tamasfe.even-better-toml",
        "usernamehw.errorlens",
        "withfig.fig"
    ]
}